setup.py
distributions/Binomialdistribution.py
distributions/Gaussiandistribution.py
distributions/Generaldistribution.py
distributions/__init__.py
qnga.egg-info/PKG-INFO
qnga.egg-info/SOURCES.txt
qnga.egg-info/dependency_links.txt
qnga.egg-info/not-zip-safe
qnga.egg-info/top_level.txt